listings_db_api_client/__init__.py
listings_db_api_client/listings_db_api_client.py
listings_db_api_client-1.0.5.dist-info/METADATA
listings_db_api_client-1.0.5.dist-info/WHEEL
listings_db_api_client-1.0.5.dist-info/top_level.txt
listings_db_api_client-1.0.5.dist-info/RECORD
