Metadata-Version: 2.4
Name: listings-db-api-client
Version: 1.0.5
Summary: Python client library for the Finder property listings database API
Author-email: giacomokavanagh <giacomokavanagh@gmail.com>
Project-URL: Homepage, https://github.com/giacomokavanagh/listings-db-mcp
Project-URL: Bug Tracker, https://github.com/giacomokavanagh/listings-db-mcp/issues
Classifier: Development Status :: 4 - Beta
Classifier: Intended Audience :: Developers
Classifier: License :: OSI Approved :: MIT License
Classifier: Operating System :: OS Independent
Classifier: Programming Language :: Python :: 3
Classifier: Programming Language :: Python :: 3.12
Requires-Python: >=3.12
Requires-Dist: httpx>=0.24.0
Requires-Dist: python-dotenv>=1.1.0
Requires-Dist: listings-db-contracts>=1.0.3
